jupyter_midi_player-0.6.0.dist-info/licenses/LICENSE
midi_player/__init__.py
midi_player/midi_player.py
midi_player/stylers.py
midi_player/static/js/focus-visible.js
midi_player/static/js/html-midi-player.js
midi_player/static/js/magenta-music.js
midi_player/static/js/tone.min.js
jupyter_midi_player-0.6.0.dist-info/METADATA
jupyter_midi_player-0.6.0.dist-info/WHEEL
jupyter_midi_player-0.6.0.dist-info/top_level.txt
jupyter_midi_player-0.6.0.dist-info/RECORD
