Metadata-Version: 2.4
Name: jupyter-midi-player
Version: 0.6.0
Summary: Python launcher of animated MIDI player by @cifkao & @magenta
Home-page: https://github.com/drscotthawley/midi-player
Author: Scott H. Hawley
Author-email: scott.hawley@belmont.edu
License: MIT
Project-URL: Source, https://github.com/drscotthawley/midi-player
License-File: LICENSE
Dynamic: author
Dynamic: author-email
Dynamic: description
Dynamic: description-content-type
Dynamic: home-page
Dynamic: license
Dynamic: license-file
Dynamic: project-url
Dynamic: summary
